<Properties StartupConfiguration="{AB17BD71-F8F5-FE43-26DF-26925648DFC9}|">
  <MonoDevelop.Ide.Workbench ActiveDocument="Assets/Scripts/Loco.cs">
    <Files>
      <File FileName="Assets/Scripts/Follower.cs" Line="1" Column="1" />
      <File FileName="Assets/Scripts/RotateCamera.cs" Line="17" Column="6" />
      <File FileName="Assets/Scripts/SpawnTrain.cs" Line="23" Column="10" />
      <File FileName="Assets/Scripts/Loco.cs" Line="5" Column="16" />
    </Files>
    <Pads>
      <Pad Id="ProjectPad">
        <State name="__root__">
          <Node name="Idle Transport" expanded="True">
            <Node name="Assets" expanded="True">
              <Node name="Scripts" expanded="True">
                <Node name="Loco.cs" selected="True" />
              </Node>
            </Node>
          </Node>
        </State>
      </Pad>
    </Pads>
  </MonoDevelop.Ide.Workbench>
  <MonoDevelop.Ide.DebuggingService.PinnedWatches />
  <MonoDevelop.Ide.Workspace ActiveConfiguration="Debug" />
  <MonoDevelop.Ide.ItemProperties.Assembly-CSharp PreferredExecutionTarget="baf8c3a3-2f3e-439b-9e8d-3cb40e5cccfc" />
  <MonoDevelop.Ide.DebuggingService.Breakpoints>
    <BreakpointStore />
  </MonoDevelop.Ide.DebuggingService.Breakpoints>
  <MultiItemStartupConfigurations />
</Properties>